<?xml version="1.0"?>
<PropertyList>
	<scenario>
		<description>
			
			Places the original LODI and the TABOR ferries on the Lake of Constance 
      near Konstanz and Meersburg (next Airport is Friedrichshafen: EDNY)

			TACAN Lodi  32X
      TACAN Tabor 32Y
		</description>

		<entry>
			<type>carrier</type>
			<name>Lodi</name>
			<pennant-number>SW1</pennant-number>
			<TACAN-channel-ID>32X</TACAN-channel-ID>
			<model>Models/Geometry/Bodensee/lodi.xml</model>
			<latitude>47.694837</latitude>
			<longitude>9.264661</longitude>
			<heading>305</heading>
			<altitude>1286</altitude>
			<speed>0</speed>
			<rudder>0</rudder>
			<turn-radius-ft>50</turn-radius-ft>
			<parking-pos>
				<name>cat</name>
				<x-offset-m>-4.6843</x-offset-m>
				<y-offset-m>0.0</y-offset-m>
				<z-offset-m>3.0</z-offset-m>
			</parking-pos>
			<parking-pos>
				<name>H1</name>
				<x-offset-m>0</x-offset-m>
				<y-offset-m>0</y-offset-m>
				<z-offset-m>31.5</z-offset-m>
			</parking-pos>
			<max-lat>0.01</max-lat>
			<min-lat>0.05</min-lat>
			<max-long>0.05</max-long>
			<min-long>0.01</min-long>
			<mp-control>false</mp-control>
			<ai-control>true</ai-control>
		</entry>

		<entry>
			<type>carrier</type>
			<name>Tabor</name>
			<pennant-number>SW2</pennant-number>
			<TACAN-channel-ID>32Y</TACAN-channel-ID>
			<model>Models/Geometry/Bodensee/tabor.xml</model>
			<latitude>47.683939</latitude>
			<longitude>9.215813</longitude>
			<heading>75</heading>
			<altitude>1286</altitude>
			<speed>0</speed>
			<rudder>0</rudder>
			<turn-radius-ft>50</turn-radius-ft>
			<parking-pos>
				<name>cat</name>
				<x-offset-m>-4.6843</x-offset-m>
				<y-offset-m>0.0</y-offset-m>
				<z-offset-m>3.0</z-offset-m>
			</parking-pos>
			<parking-pos>
				<name>H1</name>
				<x-offset-m>0</x-offset-m>
				<y-offset-m>0</y-offset-m>
				<z-offset-m>31.5</z-offset-m>
			</parking-pos>
			<max-lat>0.01</max-lat>
			<min-lat>0.05</min-lat>
			<max-long>0.05</max-long>
			<min-long>0.01</min-long>
			<mp-control>false</mp-control>
			<ai-control>true</ai-control>
		</entry>

		<entry>
			<type>groundvehicle</type>
			<model>Models/Geometry/Bodensee/horse_wernico.xml</model>
			<name>Wernico</name>
	    <flightplan>horses_1.xml</flightplan>
			<restart>1</restart>
			<turn-radius-ft>50</turn-radius-ft>
			<fixed-turn-radius-ft>20</fixed-turn-radius-ft>
			<lead-angle-gain>1</lead-angle-gain>
			<lead-angle-limit-deg>5.0</lead-angle-limit-deg>
			<lead-angle-proportion>0.5</lead-angle-proportion>
			<rudder-constant>50</rudder-constant>
			<speed-constant>3</speed-constant>
			<pitch-coefficient>0.1</pitch-coefficient>
			<elevation-coefficient>0.1</elevation-coefficient>
			<tow-angle-gain>0.25</tow-angle-gain>
			<tow-angle-limit-deg>1.0</tow-angle-limit-deg>
			<contact-x1-offset>-31.21</contact-x1-offset>
			<contact-x2-offset>31.21</contact-x2-offset>
			<hitch-x-offset>39.70964</hitch-x-offset>
		</entry>

		<entry>
			<type>groundvehicle</type>
			<model>Models/Geometry/Bodensee/horse_alouette.xml</model>
			<name>Alouette</name>
	    <flightplan>horses.xml</flightplan>
			<restart>1</restart>
			<turn-radius-ft>50</turn-radius-ft>
			<fixed-turn-radius-ft>20</fixed-turn-radius-ft>
			<lead-angle-gain>1</lead-angle-gain>
			<lead-angle-limit-deg>5.0</lead-angle-limit-deg>
			<lead-angle-proportion>0.5</lead-angle-proportion>
			<rudder-constant>50</rudder-constant>
			<speed-constant>3</speed-constant>
			<pitch-coefficient>0.1</pitch-coefficient>
			<elevation-coefficient>0.1</elevation-coefficient>
			<tow-angle-gain>0.25</tow-angle-gain>
			<tow-angle-limit-deg>1.0</tow-angle-limit-deg>
			<contact-x1-offset>-31.21</contact-x1-offset>
			<contact-x2-offset>31.21</contact-x2-offset>
			<hitch-x-offset>39.70964</hitch-x-offset>
		</entry>

		<entry>
			<type>carrier</type>
			<name>MSUBS</name>
			<pennant-number>CH1</pennant-number>
			<TACAN-channel-ID>031Y</TACAN-channel-ID>
			<model>Models/Geometry/Nimitz/eisenhower.xml</model>
			<latitude>47.221</latitude>
			<longitude>8.721</longitude>
			<speed>0</speed>
			<heading>85</heading>
			<altitude>1300</altitude>
			<rudder>0</rudder>
			<turn-radius-ft>12000</turn-radius-ft>
			<flols-pos>
				<x-offset-m>69.84</x-offset-m>
				<y-offset-m>-39.67</y-offset-m>
				<z-offset-m>21.47</z-offset-m>
			</flols-pos>
			<parking-pos>
				<name>cat-1</name>
				<heading-offset-deg>-4</heading-offset-deg>
				<x-offset-m>-3.65</x-offset-m>
				<y-offset-m>15.2715</y-offset-m>
				<z-offset-m>20</z-offset-m>
			</parking-pos>
			<parking-pos>
				<name>cat-2</name>
				<heading-offset-deg>-1</heading-offset-deg>
				<x-offset-m>1.6</x-offset-m>
				<y-offset-m>-4.6</y-offset-m>
				<z-offset-m>20</z-offset-m>
			</parking-pos>
			<parking-pos>
				<name>cat-3</name>
				<heading-offset-deg>-4</heading-offset-deg>
				<x-offset-m>93</x-offset-m>
				<y-offset-m>-20.2362</y-offset-m>
				<z-offset-m>20</z-offset-m>
			</parking-pos>
			<parking-pos>
				<name>cat-4</name>
				<heading-offset-deg>0</heading-offset-deg>
				<x-offset-m>110</x-offset-m>
				<y-offset-m>-29.6417</y-offset-m>
				<z-offset-m>20</z-offset-m>
			</parking-pos>
			<parking-pos>
				<name>park-1</name>
				<heading-offset-deg>-90</heading-offset-deg>
				<x-offset-m>54</x-offset-m>
				<y-offset-m>26</y-offset-m>
				<z-offset-m>20</z-offset-m>
			</parking-pos>
			<max-lat>0.01</max-lat>
			<min-lat>0.05</min-lat>
			<max-long>0.05</max-long>
			<min-long>0.01</min-long>
			<mp-control>false</mp-control>
			<ai-control>true</ai-control>
		</entry>
	</scenario>
</PropertyList>
